LICENSE
MANIFEST.in
README.md
setup.cfg
setup.py
tests/test_lidar.py
tests/test_vmas.py
vmas/__init__.py
vmas/interactive_rendering.py
vmas/make_env.py
vmas.egg-info/PKG-INFO
vmas.egg-info/SOURCES.txt
vmas.egg-info/dependency_links.txt
vmas.egg-info/requires.txt
vmas.egg-info/top_level.txt
vmas/examples/__init__.py
vmas/examples/rllib.py
vmas/examples/run_heuristic.py
vmas/examples/use_vmas_env.py
vmas/scenarios/__init__.py
vmas/scenarios/balance.py
vmas/scenarios/ball_passage.py
vmas/scenarios/ball_trajectory.py
vmas/scenarios/buzz_wire.py
vmas/scenarios/discovery.py
vmas/scenarios/dispersion.py
vmas/scenarios/dropout.py
vmas/scenarios/flocking.py
vmas/scenarios/football.py
vmas/scenarios/give_way.py
vmas/scenarios/joint_passage.py
vmas/scenarios/joint_passage_size.py
vmas/scenarios/multi_give_way.py
vmas/scenarios/navigation.py
vmas/scenarios/passage.py
vmas/scenarios/reverse_transport.py
vmas/scenarios/road_traffic.py
vmas/scenarios/sampling.py
vmas/scenarios/transport.py
vmas/scenarios/wheel.py
vmas/scenarios/wind_flocking.py
vmas/scenarios/debug/__init__.py
vmas/scenarios/debug/asym_joint.py
vmas/scenarios/debug/circle_trajectory.py
vmas/scenarios/debug/diff_drive.py
vmas/scenarios/debug/drone.py
vmas/scenarios/debug/goal.py
vmas/scenarios/debug/het_mass.py
vmas/scenarios/debug/kinematic_bicycle.py
vmas/scenarios/debug/line_trajectory.py
vmas/scenarios/debug/pollock.py
vmas/scenarios/debug/vel_control.py
vmas/scenarios/debug/waterfall.py
vmas/scenarios/mpe/__init__.py
vmas/scenarios/mpe/simple.py
vmas/scenarios/mpe/simple_adversary.py
vmas/scenarios/mpe/simple_crypto.py
vmas/scenarios/mpe/simple_push.py
vmas/scenarios/mpe/simple_reference.py
vmas/scenarios/mpe/simple_speaker_listener.py
vmas/scenarios/mpe/simple_spread.py
vmas/scenarios/mpe/simple_tag.py
vmas/scenarios/mpe/simple_world_comm.py
vmas/scenarios_data/road_traffic/road_traffic_cpm_lab.xml
vmas/simulator/__init__.py
vmas/simulator/core.py
vmas/simulator/heuristic_policy.py
vmas/simulator/joints.py
vmas/simulator/physics.py
vmas/simulator/rendering.py
vmas/simulator/scenario.py
vmas/simulator/secrcode.ttf
vmas/simulator/sensors.py
