Metadata-Version: 2.4
Name: vmas
Version: 1.5.2
Summary: Vectorized Multi-Agent Simulator
Home-page: https://github.com/proroklab/VectorizedMultiAgentSimulator
Author: Matteo Bettini
Author-email: mb2389@cl.cam.ac.uk
License: GPLv3
License-File: LICENSE
Requires-Dist: numpy
Requires-Dist: torch
Requires-Dist: pyglet<=1.5.27
Requires-Dist: gym
Requires-Dist: gym-notices==0.0.8
Requires-Dist: six
Provides-Extra: gymnasium
Requires-Dist: gymnasium; extra == "gymnasium"
Requires-Dist: shimmy; extra == "gymnasium"
Provides-Extra: rllib
Requires-Dist: ray[rllib]<=2.2; extra == "rllib"
Provides-Extra: render
Requires-Dist: opencv-python; extra == "render"
Requires-Dist: moviepy; extra == "render"
Requires-Dist: matplotlib; extra == "render"
Requires-Dist: opencv-python; extra == "render"
Provides-Extra: test
Requires-Dist: pytest; extra == "test"
Requires-Dist: pytest-instafail; extra == "test"
Requires-Dist: pyyaml; extra == "test"
Requires-Dist: tqdm; extra == "test"
Dynamic: author
Dynamic: author-email
Dynamic: home-page
Dynamic: license
Dynamic: license-file
Dynamic: provides-extra
Dynamic: requires-dist
Dynamic: summary
